hopprclient/__init__.py
hopprclient/__main__.py
hopprclient/hoppr_client.py
hopprclient/dicom/__init__.py
hopprclient/dicom/__main__.py
hopprclient/dicom/dicom_tag_deid.py
hopprclient/dicom/sop_class_spider.py
hopprclient/dicom/sop_module_spider.py
hopprclient/service_clients/__init__.py
hopprclient/service_clients/files_service_client.py
hopprclient/service_clients/http_service_client.py
hopprclient-0.1.6.dist-info/LICENSE
hopprclient-0.1.6.dist-info/METADATA
hopprclient-0.1.6.dist-info/WHEEL
hopprclient-0.1.6.dist-info/entry_points.txt
hopprclient-0.1.6.dist-info/top_level.txt
hopprclient-0.1.6.dist-info/RECORD
