Metadata-Version: 2.1
Name: hopprclient
Version: 0.1.6
Summary: Application to upload datasets to the HOPPR servers
Home-page: https://www.hoppr.ai/
Author: Jack Cosgrove
Author-email: jack@hoppr.ai
License: MIT
Platform: UNKNOWN
Classifier: License :: OSI Approved :: MIT License
Classifier: Programming Language :: Python :: 3.6
